mip2/__init__.py
mip2/api.cpython-311-x86_64-linux-gnu.so
mip2/api.pyi
mip2/cbc.cpython-311-x86_64-linux-gnu.so
mip2/cbc.pyi
mip2/cbc_ms.cpython-311-x86_64-linux-gnu.so
mip2/cbc_ms.pyi
mip2/scip.cpython-311-x86_64-linux-gnu.so
mip2/scip.pyi
mip2-1.0.0.dist-info/METADATA
mip2-1.0.0.dist-info/WHEEL
mip2-1.0.0.dist-info/licenses/LICENSE
mip2-1.0.0.dist-info/RECORD
