Metadata-Version: 2.3
Name: mip2
Version: 1.0.0
Summary: A mixed integer modeling tool with code style similar to gurobi
Project-URL: Homepage, https://pypi.org/manage/projects/
Project-URL: Issues, https://pypi.org/manage/projects/
Author-email: allen2233 <author@example.com>
License-File: LICENSE
Classifier: License :: OSI Approved :: MIT License
Classifier: Operating System :: OS Independent
Classifier: Programming Language :: Python :: 3
Requires-Python: >=3.8
